iqm/server/proto/__init__.py
iqm/server/proto/calibration_pb2.py
iqm/server/proto/calibration_pb2.pyi
iqm/server/proto/calibration_pb2_grpc.py
iqm/server/proto/common_pb2.py
iqm/server/proto/common_pb2.pyi
iqm/server/proto/common_pb2_grpc.py
iqm/server/proto/job_pb2.py
iqm/server/proto/job_pb2.pyi
iqm/server/proto/job_pb2_grpc.py
iqm/server/proto/qc_pb2.py
iqm/server/proto/qc_pb2.pyi
iqm/server/proto/qc_pb2_grpc.py
iqm/server/proto/uuid_pb2.py
iqm/server/proto/uuid_pb2.pyi
iqm/server/proto/uuid_pb2_grpc.py
iqm_server_data_definitions-1.8.dist-info/LICENSE.txt
iqm_server_data_definitions-1.8.dist-info/METADATA
iqm_server_data_definitions-1.8.dist-info/WHEEL
iqm_server_data_definitions-1.8.dist-info/RECORD
